deprecated/hello.py
dune_analytics_mcp-0.1.0.dist-info/licenses/LICENSE
dune_analytics_mcp-0.1.0.dist-info/METADATA
dune_analytics_mcp-0.1.0.dist-info/WHEEL
dune_analytics_mcp-0.1.0.dist-info/top_level.txt
dune_analytics_mcp-0.1.0.dist-info/RECORD
